kan_sdk/__init__.py
kan_sdk/main.py
kan_sdk-0.0.2.dist-info/METADATA
kan_sdk-0.0.2.dist-info/WHEEL
kan_sdk-0.0.2.dist-info/top_level.txt
kan_sdk-0.0.2.dist-info/RECORD
