Metadata-Version: 2.1
Name: kan-sdk
Version: 0.0.2
Summary: UNKNOWN
Home-page: https://github.com/kan-fun/kan-python
Author: kan
License: UNKNOWN
Platform: UNKNOWN
Requires-Dist: requests
